localrouter/__init__.py
localrouter/dtypes.py
localrouter/llm.py
localrouter/utils.py
localrouter/xml_utils.py
localrouter-0.2.15.dist-info/METADATA
localrouter-0.2.15.dist-info/WHEEL
localrouter-0.2.15.dist-info/top_level.txt
localrouter-0.2.15.dist-info/RECORD
