Metadata-Version: 2.4
Name: localrouter
Version: 0.2.15
Summary: Multi-provider LLM client with unified message format and tool support
Author: Center on Long-term Risk
Classifier: Development Status :: 4 - Beta
Classifier: Intended Audience :: Developers
Classifier: License :: OSI Approved :: MIT License
Classifier: Programming Language :: Python :: 3
Classifier: Programming Language :: Python :: 3.11
Classifier: Programming Language :: Python :: 3.12
Requires-Python: >=3.11
Requires-Dist: anthropic>=0.50.0
Requires-Dist: backoff>=2.2.1
Requires-Dist: openai>=1.98.0
Requires-Dist: pydantic>=2.7.0
Requires-Dist: python-dotenv>=1.0.0
Requires-Dist: pyyaml>=6.0.2
Requires-Dist: cache_on_disk>=0.5.0
Requires-Dist: google-genai>=1.26.0
Provides-Extra: images
Requires-Dist: Pillow>=10.0.0; extra == "images"
Provides-Extra: dev
Requires-Dist: pytest>=7.0.0; extra == "dev"
Requires-Dist: pytest-asyncio>=0.21.0; extra == "dev"
Requires-Dist: pre-commit>=4.0.0; extra == "dev"
Requires-Dist: black>=25.0.0; extra == "dev"
